wandb_logger-0.1.1.dist-info/licenses/LICENSE
wandb_logger_app/__init__.py
wandb_logger_app/config.py
wandb_logger_app/main.py
wandb_logger_app/utils.py
wandb_logger_app/wandb_api.py
wandb_logger_app/commands/__init__.py
wandb_logger_app/commands/auth_commands.py
wandb_logger_app/commands/fetch_command.py
wandb_logger_app/commands/recent_command.py
wandb_logger_app/commands/recent_runs_command.py
wandb_logger_app/commands/utility_commands.py
wandb_logger_app/data/.gitkeep
wandb_logger_app/data/.cache/h41royyx.json
wandb_logger_app/data/.cache/ia5zcc3a.json
wandb_logger_app/data/.cache/yq7uz46j.json
wandb_logger_app/data/Only_VD:all-1epochs/Only_VD:all-1epochs.md
wandb_logger_app/data/Only_VD:all-1epochs/metadata.md
wandb_logger_app/data/Only_VD:all-1epochs/train_grad_norm.png
wandb_logger_app/data/Only_VD:all-1epochs/train_loss.png
wandb_logger_app/ui/console.py
wandb_logger-0.1.1.dist-info/METADATA
wandb_logger-0.1.1.dist-info/WHEEL
wandb_logger-0.1.1.dist-info/entry_points.txt
wandb_logger-0.1.1.dist-info/top_level.txt
wandb_logger-0.1.1.dist-info/RECORD
