Metadata-Version: 2.4
Name: wandb-logger
Version: 0.1.1
Summary: A command-line tool for managing Weights & Biases (W&B) training logs
Home-page: https://github.com/SabaPivot/wandb-logger
Author: SabaPivot
Author-email: SabaPivot <careforme.dropout@gmail.com>
License: MIT
Project-URL: Homepage, https://github.com/SabaPivot/wandb-logger
Project-URL: Repository, https://github.com/SabaPivot/wandb-logger.git
Requires-Python: >=3.8
License-File: LICENSE
Requires-Dist: click>=8.0.0
Requires-Dist: wandb>=0.12.0
Requires-Dist: rich>=10.0.0
Requires-Dist: pandas>=1.0.0
Requires-Dist: matplotlib>=3.0.0
Requires-Dist: seaborn>=0.11.0
Dynamic: author
Dynamic: home-page
Dynamic: license-file
Dynamic: requires-python
